{
  "tweets": [
    {
      "id": 124,
      "sender": {
        "id": "@BillGates",
        "name": "بیل گیتس",
        "image": "/images/users/01.png"
      },
      "text": "بونو، شما به همان اندازه که یک دوست هستید یک انسان دوست شگفت انگیز هستید. کار کردن و یادگیری با هم یکی از بزرگترین لذت های من بوده است.",
      "like": 78
    },
    {
      "id": 123,
      "sender": {
        "id": "@tesla",
        "name": "تسلا",
        "image": "/images/users/02.png"
      },
      "text": "ما تنها در یک دهه نزدیک به 100 هزار شغل جدید مستقیم ایجاد کردیم - و در حال برنامه ریزی برای رشد برای سال های آینده هستیم.",
      "like": 234
    },
    {
      "id": 785,
      "sender": {
        "id": "@vahid",
        "name": "وحید احمدی",
        "image": "/images/users/03.png"
      },
      "text": "مشتری‌های خود را در بازار داریم و بازارهای جدیدی را هم شناسایی‌ کرد‌ه‌ایم‌ که این روند با قوت ادامه می‌یابد.",
      "like": 4
    },
    {
      "id": 703,
      "sender": {
        "id": "@azariJahromi",
        "name": "آذری جهرمی",
        "image": "/images/users/04.png"
      },
      "text": "فکر کن در یک بازی ۵ بر صفر جلو باشی، بعد نتیجه بشود ۵ بریک. حس ما پرسپولیسی‌ها اینطوری است",
      "like": 78
    },
    {
      "id": 986,
      "sender": {
        "id": "@zarif",
        "name": "محمد جواد ظریف",
        "image": "/images/users/05.png"
      },
      "text": "آنهایی که خود را به شکل دیپلمات درآورده‌اند و آنهایی که به صورت بی‌شرمانه نشسته‌اند تا اهداف فرهنگی و غیرنظامی ایران را شناسایی کنند، حتی زحمت بازکردن فرهنگ لغات حقوقی را به خود نداده‌اند.",
      "like": 78
    },
    {
      "id": 986,
      "sender": {
        "id": "@digiKala",
        "name": "دیجیکالا",
        "image": "/images/users/06.png"
      },
      "text": "بررسی، انتخاب، خرید آنلاین | حساب کاربری رسمی فروشگاه اینترنتی دیجی‌کالا | لطفا برای ارسال پیام با این اکانت در ارتباط باشید.",
      "like": 78
    },
    {
      "id": 986,
      "sender": {
        "id": "@arash1350",
        "name": "آرش علوی",
        "image": "/images/users/07.png"
      },
      "text": "بعد از بالیدن به جعبه خالی‌تون و نقاشی کشیدن ازش، میشه به سطح سرویس‌تون هم فکر کنید و ‌پول مردمی که چندماه منتظر هستن رو پس بدید؟ دم شما گرم.",
      "like": 78
    },
    {
      "id": 986,
      "sender": {
        "id": "@ElonMusk",
        "name": "ایلان ماسک",
        "image": "/images/users/08.png"
      },
      "text": "به این وسیله ولادیمیر پوتین را به نبردی تن به تن دعوت می‌کنم. شرط بر سر اوکراین است.",
      "like": 78
    },
    {
      "id": 986,
      "sender": {
        "id": "@hasanRouhani",
        "name": "حسن روحانی",
        "image": "/images/users/09.png"
      },
      "text": "استاد محمدرضا #شجریان چهره برجسته هنری و آفریننده ماندگارترین نواهای دلنشین ایرانی و خواننده ربنای رمضان، ميراث ارزشمندی از خود به یادگار گذاشت. یقیناً ملت قدرشناس ایران، نام و یاد و آثار اين هنرمند محبوب را همواره در خاطره‌ها، زنده نگاه خواهد داشت. روحش شاد و یادش گرامی",
      "like": 78
    },
    {
      "id": 986,
      "sender": {
        "id": "@maryam69335",
        "name": "مریم مینایی",
        "image": "/images/users/10.png"
      },
      "text": "سنگربان ملی‌پوش پورتیموننزه در سالی که به جام جهانی 2022 قطر منتهی می‌شود فقط در تیمی بازی خواهد کرد که به او تضمین بازی داده شود.",
      "like": 78
    }
  ],
  "hashtags": [
    "استقلال",
    "سیگار",
    "احساس_خوب",
    "خودرو_ملی",
    "نمایشگاه_کتاب",
    "لیگ_ایتالیا",
    "فرهاد_مجیدی"
  ],
  "users": [
    {
      "id": "@maryam69335",
      "name": "مریم مینایی",
      "image": "/images/users/10.png"
    },
    {
      "id": "@hasanRouhani",
      "name": "حسن روحانی",
      "image": "/images/users/09.png"
    },
    {
      "id": "@ElonMusk",
      "name": "ایلان ماسک",
      "image": "/images/users/08.png"
    },
    {
      "id": "@arash1350",
      "name": "آرش علوی",
      "image": "/images/users/07.png"
    },
    {
      "id": "@digiKala",
      "name": "دیجیکالا",
      "image": "/images/users/06.png"
    },
    {
      "id": "@zarif",
      "name": "محمد جواد ظریف",
      "image": "/images/users/05.png"
    },
    {
      "id": "@azariJahromi",
      "name": "آذری جهرمی",
      "image": "/images/users/04.png"
    },
    {
      "id": "@vahid",
      "name": "وحید احمدی",
      "image": "/images/users/03.png"
    },
    {
      "id": "@tesla",
      "name": "تسلا",
      "image": "/images/users/02.png"
    },
    {
      "id": "@BillGates",
      "name": "بیل گیتس",
      "image": "/images/users/01.png"
    }
  ]
}